dev_project/__init__.py
dev_project/settings.py
dev_project/urls.py
tenanet/__init__.py
tenanet/admin.py
tenanet/apps.py
tenanet/context_processors.py
tenanet/managers.py
tenanet/middleware.py
tenanet/models.py
tenanet/settings.py
tenanet/signals.py
tenanet/urls.py
tenanet/utility.py
tenanet/views.py
tenanet/api/__init__.py
tenanet/management/__init__.py
tenanet/management/commands/__init__.py
tenanet/management/commands/tenanet.py
tenanet/migrations/0001_initial.py
tenanet/migrations/0002_rename_usertenantassociation_tenantuserassociation_and_more.py
tenanet/migrations/0003_remove_tenant_short_name_tenantconfiguration_logo_and_more.py
tenanet/migrations/0004_tenantmeta.py
tenanet/migrations/__init__.py
tenanet/templates/tenant_switcher.html
tenanet/tests/__init__.py
tenanet/tests/tests.py
django_tenanet-0.1.1.dist-info/LICENSE
django_tenanet-0.1.1.dist-info/METADATA
django_tenanet-0.1.1.dist-info/WHEEL
django_tenanet-0.1.1.dist-info/top_level.txt
django_tenanet-0.1.1.dist-info/RECORD
