Metadata-Version: 2.1
Name: django-tenanet
Version: 0.1.1
Summary: A Django app for multi-tenancy.
Home-page: https://github.com/rsjsoc/django-tenanet
Author: He0468
Author-email: rsjsoc@gmail.com
License: Custom License: Django-Tenanet Limited Use License
Classifier: Environment :: Web Environment
Classifier: Framework :: Django
Classifier: Framework :: Django :: 4.0
Classifier: Intended Audience :: Developers
Classifier: License :: Other/Proprietary License
Classifier: Operating System :: OS Independent
Classifier: Programming Language :: Python
Classifier: Programming Language :: Python :: 3
Classifier: Programming Language :: Python :: 3.11
Classifier: Topic :: Internet :: WWW/HTTP
Classifier: Topic :: Internet :: WWW/HTTP :: Dynamic Content
License-File: LICENSE
Requires-Dist: Django >=4.0
